flask_logify/__init__.py
flask_logify/filters.py
flask_logify/formatters.py
flask_logify/handlers.py
flask_logify/logging.py
flask_logify/version.py
flask_logify/builders/__init__.py
flask_logify/builders/base.py
flask_logify/builders/json.py
flask_logify/builders/text.py
Flask_Logify-2.4.5.dist-info/LICENSE
Flask_Logify-2.4.5.dist-info/METADATA
Flask_Logify-2.4.5.dist-info/WHEEL
Flask_Logify-2.4.5.dist-info/top_level.txt
Flask_Logify-2.4.5.dist-info/RECORD
